{"scripts": [{"id": "UXVT6ajx", "text": "\u2764\ufe0f\u0421\u043a\u0440\u0438\u043f\u0442 \u043e\u0442 @kreahub\n\nGame: \n<blockquote>Deal Rails</blockquote>\n\nScript\n<pre>loadstring(game:HttpGet(&quot;https://raw.githubusercontent.com/JonasThePogi/DeadRails/refs/heads/main/Protected_2770441711245817.txt&quot;))()</pre>\n\n\u041e\u043f\u0438\u0441\u0430\u043d\u0438\u0435\n<blockquote>Teleport</blockquote>", "photo": null, "creator_id": 2080989762}, {"id": "y4EeCY04", "text": "\u2764\ufe0f\u0421\u043a\u0440\u0438\u043f\u0442 \u043e\u0442 @kreahub\n\nGame: \n<blockquote>Murder Mystery 2</blockquote>\n\nScript\n<pre><code class=\"lua\">loadstring(game:HttpGet(&quot;https://raw.githubusercontent.com/Aura-56/MurderMystery2/refs/heads/main/Autofarm.lua&quot;, true))()</code></pre>\n\n\u041e\u043f\u0438\u0441\u0430\u043d\u0438\u0435\n<blockquote>Auto Farm Candy, Auto Reset</blockquote>", "photo": null, "creator_id": 2080989762}, {"id": "2yDpmlBH", "text": "\u2764\ufe0f\u0421\u043a\u0440\u0438\u043f\u0442 \u043e\u0442 @kreahub\n\nGame: \n<blockquote>Da Hood</blockquote>\n\nScript\n<pre><code class=\"lua\">loadstring(game:HttpGet(&quot;https://pastebin.com/raw/XhYL8Zvv&quot;))()</code></pre>\n\n\u041e\u043f\u0438\u0441\u0430\u043d\u0438\u0435\n<blockquote>Multiple Scripts</blockquote>", "photo": null, "creator_id": 2080989762}, {"id": "zIFNHPMJ", "text": "\u2764\ufe0f\u0421\u043a\u0440\u0438\u043f\u0442 \u043e\u0442 @kreahub\n\nGame: \n<blockquote>Steal a Brainrot</blockquote>\n\nScript\n<pre><code class=\"lua\">script_key=&quot;PUT YOUR KEY HERE&quot;;\nloadstring(game:HttpGet(&quot;https://pastefy.app/MJw2J4T6/raw&quot;))()</code></pre>\n\n\u041e\u043f\u0438\u0441\u0430\u043d\u0438\u0435\n<blockquote>Super Speed, NO KEY, High Jump</blockquote>", "photo": null, "creator_id": 2080989762}]}